chimp_detector/__init__.py
chimp_detector/helper/__init__.py
chimp_detector/helper/audio_processor.py
chimp_detector/helper/chimp_detector.py
chimp_detector/helper/config.py
chimp_detector/helper/featuremap_processor.py
chimp_detector/helper/predictor.py
chimp_detector/helper/data/DATE:2022-01-28_15:51:39_CLASS:drumming_TestF1:0.379/saved_model.pb
chimp_detector/helper/data/DATE:2022-01-28_15:51:39_CLASS:drumming_TestF1:0.379/variables/variables.data-00000-of-00001
chimp_detector/helper/data/DATE:2022-01-28_15:51:39_CLASS:drumming_TestF1:0.379/variables/variables.index
ChimpDrummingDetector-0.0.3.dist-info/LICENSE
ChimpDrummingDetector-0.0.3.dist-info/METADATA
ChimpDrummingDetector-0.0.3.dist-info/WHEEL
ChimpDrummingDetector-0.0.3.dist-info/top_level.txt
ChimpDrummingDetector-0.0.3.dist-info/RECORD
