Metadata-Version: 2.1
Name: ChimpDrummingDetector
Version: 0.0.3
Summary: A program for detecting chimpanzee drumming in long-term rainforest recordings
Home-page: https://github.com/andersfranzanders/chimp_drumming_detector_small
Author: Franz Anders
Author-email: franz.anders.fa@gmail.com
License: 'MIT'
Platform: UNKNOWN
Requires-Python: >=3.8
License-File: LICENSE
Requires-Dist: librosa (==0.8.0)
Requires-Dist: tensorflow (==2.3.1)
Requires-Dist: pandas (==1.1.2)
Requires-Dist: numpy (==1.18.5)
